machina_observatrix/__init__.py
machina_observatrix/githf.py
machina_observatrix/machina.yaml
machina_observatrix-0.0.3.dist-info/LICENSE
machina_observatrix-0.0.3.dist-info/METADATA
machina_observatrix-0.0.3.dist-info/WHEEL
machina_observatrix-0.0.3.dist-info/top_level.txt
machina_observatrix-0.0.3.dist-info/RECORD
